pyrello/__init__.py
pyrello/configure.py
pyrello/pyrello.py
pyrello-1.1.1.dist-info/METADATA
pyrello-1.1.1.dist-info/RECORD
pyrello-1.1.1.dist-info/WHEEL
pyrello-1.1.1.dist-info/entry_points.txt
pyrello-1.1.1.dist-info/top_level.txt
