Metadata-Version: 2.1
Name: pyrello
Version: 1.1.1
Summary: Export Kanban metrics as a CSV file for Trello Boards
Home-page: UNKNOWN
Author: Leandro Mattoso
Author-email: lcmattoso@gmail.com
License: UNKNOWN
Keywords: kanban trello metrics leadtime throughput cfd agile
Platform: UNKNOWN
Classifier: Development Status :: 3 - Alpha
Classifier: Intended Audience :: Developers
Classifier: Topic :: Utilities
Classifier: License :: OSI Approved :: MIT License
Classifier: Programming Language :: Python :: 3
Classifier: Programming Language :: Python :: 3.4
Classifier: Programming Language :: Python :: 3.5
Classifier: Programming Language :: Python :: 3.6
Requires-Dist: requests
